pytest_squadcast/__init__.py
pytest_squadcast/hooks.py
pytest_squadcast/plugin.py
pytest_squadcast/squadcast.py
pytest_squadcast/__pycache__/__init__.cpython-310.pyc
pytest_squadcast-0.1.4.data/data/pytest_squadcast/__init__.cpython-310.pyc
pytest_squadcast-0.1.4.dist-info/METADATA
pytest_squadcast-0.1.4.dist-info/WHEEL
pytest_squadcast-0.1.4.dist-info/entry_points.txt
pytest_squadcast-0.1.4.dist-info/top_level.txt
pytest_squadcast-0.1.4.dist-info/RECORD
