Metadata-Version: 2.1
Name: pytest-squadcast
Version: 0.1.4
Summary: Pytest report plugin for Squadcast
Home-page: https://github.com/treussart/pytest-squadcast
Author: mtreussart
Author-email: matthieu@treussart.com
License: BSD
Keywords: py.test pytest squadcast report incident
Platform: UNKNOWN
Classifier: Development Status :: 5 - Production/Stable
Classifier: Framework :: Pytest
Classifier: Intended Audience :: Developers
Classifier: License :: OSI Approved :: BSD License
Classifier: Operating System :: OS Independent
Classifier: Natural Language :: English
Classifier: Topic :: Software Development :: Quality Assurance
Classifier: Topic :: Software Development :: Testing
Classifier: Topic :: Utilities
Classifier: Programming Language :: Python
Classifier: Programming Language :: Python :: 3
Classifier: Programming Language :: Python :: 3.7
Classifier: Programming Language :: Python :: 3.8
Classifier: Programming Language :: Python :: 3.9
Classifier: Programming Language :: Python :: 3 :: Only
Requires-Python: >=3.7
Requires-Dist: requests
Requires-Dist: pytest
